setup.py
yoda/__version__.py
yoda/draw.py
yoda/test.py
yoda/alignments/__init__.py
yoda/alignments/alignment.py
yoda/alignments/clans.py
yoda/alignments/filein.py
yoda/graphs/__init__.py
yoda/graphs/ali2graph.py
yoda/ml/__init__.py
yoda/ml/nearneigh.py
yoda/ml/nnembedder.py
yoda/ml/pairwise_alignments.py
yoda/ml/simpleMl.py
yoda/scripts/__init__.py
yoda/scripts/cluster_needle_kmer.py
yoda/scripts/inferencemodel.py
yoda/scripts/metriclearning.py
yoda/scripts/rfam_init.py
yoda/scripts/torchmetriclearn.py
yodaRNA.egg-info/PKG-INFO
yodaRNA.egg-info/SOURCES.txt
yodaRNA.egg-info/dependency_links.txt
yodaRNA.egg-info/requires.txt
yodaRNA.egg-info/top_level.txt