Metadata-Version: 2.1
Name: yodaRNA
Version: 0.0.206
Summary: rna alignmnent something something
Home-page: https://github.com/smautner/pig
Author: Stefan Mautner
Author-email: myl4stn4m3@cs.uni-freiburg.de
License: LICENSE
